[
  {
    "firstName": "Gloria",
    "lastName": "Alexander",
    "soldProducts": [
      {
        "name": "RESCRIPTOR",
        "price": 850.52,
        "buyerFirstName": "Patrick",
        "buyerLastName": "King"
      }
    ]
  },
  {
    "lastName": "Baker",
    "soldProducts": [
      {
        "name": "Azithromycin",
        "price": 813.87,
        "buyerFirstName": "Doris",
        "buyerLastName": "Cook"
      },
      {
        "name": "GEMCITABINE",
        "price": 1468.11,
        "buyerFirstName": "Jean",
        "buyerLastName": "Henry"
      },
      {
        "name": "Glipizide",
        "price": 621.78,
        "buyerFirstName": "Joshua",
        "buyerLastName": "Murray"
      },
      {
        "name": "CARBIDOPA AND LEVODOPA",
        "price": 441.64,
        "buyerFirstName": "Emily",
        "buyerLastName": "Parker"
      }
    ]
  },
  {
    "firstName": "Fred",
    "lastName": "Barnes",
    "soldProducts": [
      {
        "name": "Dawn Ultra Antibacterial Hand",
        "price": 969.86,
        "buyerFirstName": "Eugene",
        "buyerLastName": "Stewart"
      },
      {
        "name": "Eszopiclone",
        "price": 405.03,
        "buyerFirstName": "Gary",
        "buyerLastName": "Stevens"
      }
    ]
  },
  {
    "lastName": "Bennett",
    "soldProducts": [
      {
        "name": "PredniSONE",
        "price": 286.43,
        "buyerFirstName": "Bonnie",
        "buyerLastName": "Fox"
      }
    ]
  },
  {
    "firstName": "Anna",
    "lastName": "Clark",
    "soldProducts": [
      {
        "name": "LV-FX",
        "price": 820.87,
        "buyerFirstName": "Bonnie",
        "buyerLastName": "Fox"
      }
    ]
  },
  {
    "firstName": "Doris",
    "lastName": "Cook",
    "soldProducts": [
      {
        "name": "Myristica Argentum Sinus Relief",
        "price": 904.52,
        "buyerFirstName": "Jennifer",
        "buyerLastName": "Riley"
      }
    ]
  },
  {
    "firstName": "Patricia",
    "lastName": "Cooper",
    "soldProducts": [
      {
        "name": "up and up temporary minor arthritis pain relief",
        "price": 1085.78,
        "buyerFirstName": "Christine",
        "buyerLastName": "Gomez"
      }
    ]
  },
  {
    "lastName": "Cunningham",
    "soldProducts": [
      {
        "name": "Echinacea Quartz Gum Support",
        "price": 570.08,
        "buyerFirstName": "Brandon",
        "buyerLastName": "Fuller"
      }
    ]
  },
  {
    "firstName": "Carl",
    "lastName": "Daniels",
    "soldProducts": [
      {
        "name": "Pollens - Trees, Birch Mix",
        "price": 1153.54,
        "buyerLastName": "Baker"
      },
      {
        "name": "olio activ mouthwash",
        "price": 206.06,
        "buyerFirstName": "Carl",
        "buyerLastName": "Daniels"
      },
      {
        "name": "IOPE SUPER VITAL",
        "price": 824.68,
        "buyerFirstName": "Thomas",
        "buyerLastName": "Snyder"
      },
      {
        "name": "smart sense nighttime cold and flu relief",
        "price": 1101.77,
        "buyerFirstName": "Carl",
        "buyerLastName": "Lawson"
      }
    ]
  },
  {
    "firstName": "Sarah",
    "lastName": "Day",
    "soldProducts": [
      {
        "name": "Buprenorphine hydrochloride and naloxone hydrochloride dihydrate",
        "price": 293.33,
        "buyerFirstName": "Paula",
        "buyerLastName": "Hill"
      },
      {
        "name": "Strattera",
        "price": 658.54,
        "buyerFirstName": "Chris",
        "buyerLastName": "Mitchell"
      },
      {
        "name": "smart sense nicotine",
        "price": 1444.12,
        "buyerFirstName": "Chris",
        "buyerLastName": "Mitchell"
      },
      {
        "name": "Oxygen",
        "price": 1242.92,
        "buyerFirstName": "Chris",
        "buyerLastName": "Mitchell"
      }
    ]
  },
  {
    "firstName": "Clarence",
    "lastName": "Fowler",
    "soldProducts": [
      {
        "name": "Aspergillus repens",
        "price": 1231.42,
        "buyerFirstName": "Sarah",
        "buyerLastName": "Day"
      }
    ]
  },
  {
    "lastName": "Fox",
    "soldProducts": [
      {
        "name": "Buprenorphine hydrochloride",
        "price": 391.05,
        "buyerFirstName": "Gary",
        "buyerLastName": "Stevens"
      }
    ]
  },
  {
    "firstName": "Bonnie",
    "lastName": "Fox",
    "soldProducts": [
      {
        "name": "ropinirole hydrochloride",
        "price": 103.58,
        "buyerFirstName": "Jacqueline",
        "buyerLastName": "Perez"
      },
      {
        "name": "Acetaminophen, Chlorpheniramine Maleate, Dextromethorphan Hydrobromide, Phenylephrine Hydrochloride",
        "price": 1028.27,
        "buyerFirstName": "Diana",
        "buyerLastName": "Harvey"
      },
      {
        "name": "Shopko Lip Treatment",
        "price": 861.42,
        "buyerFirstName": "Betty",
        "buyerLastName": "Lawson"
      },
      {
        "name": "Hydralazine Hydrochloride",
        "price": 1309.72,
        "buyerFirstName": "Carl",
        "buyerLastName": "Lawson"
      }
    ]
  },
  {
    "firstName": "Brandon",
    "lastName": "Fuller",
    "soldProducts": [
      {
        "name": "Acid Reducer",
        "price": 1443.51,
        "buyerFirstName": "Sarah",
        "buyerLastName": "Day"
      },
      {
        "name": "Gilotrif",
        "price": 1454.77,
        "buyerFirstName": "Patricia",
        "buyerLastName": "Cooper"
      }
    ]
  },
  {
    "firstName": "Patricia",
    "lastName": "Fuller",
    "soldProducts": [
      {
        "name": "DIVALPROEX SODIUM",
        "price": 1287.03,
        "buyerFirstName": "Jennifer",
        "buyerLastName": "Riley"
      },
      {
        "name": "Trihexyphenidyl Hydrochloride",
        "price": 64.88,
        "buyerFirstName": "Brandon",
        "buyerLastName": "Fuller"
      }
    ]
  },
  {
    "firstName": "Kathy",
    "lastName": "Gilbert",
    "soldProducts": [
      {
        "name": "Goats Milk",
        "price": 298.53,
        "buyerFirstName": "Sandra",
        "buyerLastName": "Riley"
      },
      {
        "name": "PLANTAGO LANCEOLATA POLLEN",
        "price": 561.68,
        "buyerLastName": "Cunningham"
      }
    ]
  },
  {
    "firstName": "Nicole",
    "lastName": "Harris",
    "soldProducts": [
      {
        "name": "Perrigo Benzoyl Peroxide",
        "price": 873.24,
        "buyerFirstName": "Brandon",
        "buyerLastName": "Fuller"
      }
    ]
  },
  {
    "lastName": "Harrison",
    "soldProducts": [
      {
        "name": "Effervescent Cold Relief",
        "price": 1436.07,
        "buyerFirstName": "Nicole",
        "buyerLastName": "Harris"
      },
      {
        "name": "IOPE RETIGEN MOISTURE TWIN CAKE NO.21",
        "price": 1257.71,
        "buyerFirstName": "Patricia",
        "buyerLastName": "Cooper"
      },
      {
        "name": "CHAMOMILLA",
        "price": 37.97,
        "buyerFirstName": "Eugene",
        "buyerLastName": "Stewart"
      }
    ]
  },
  {
    "firstName": "Diana",
    "lastName": "Harvey",
    "soldProducts": [
      {
        "name": "AVANDAMET",
        "price": 632.08,
        "buyerFirstName": "Jacqueline",
        "buyerLastName": "Perez"
      }
    ]
  },
  {
    "firstName": "Benjamin",
    "lastName": "Henry",
    "soldProducts": [
      {
        "name": "PANTOPRAZOLE SODIUM",
        "price": 293.89,
        "buyerLastName": "Moreno"
      },
      {
        "name": "Benazepril Hydrochloride and Hydrochlorothiazide",
        "price": 1187.27,
        "buyerFirstName": "Brandon",
        "buyerLastName": "Fuller"
      }
    ]
  },
  {
    "firstName": "Paula",
    "lastName": "Hill",
    "soldProducts": [
      {
        "name": "Allopurinol",
        "price": 518.50,
        "buyerFirstName": "Chris",
        "buyerLastName": "Mitchell"
      },
      {
        "name": "Nevirapine",
        "price": 1374.72,
        "buyerFirstName": "Chris",
        "buyerLastName": "Mitchell"
      },
      {
        "name": "ENBREL",
        "price": 673.97,
        "buyerFirstName": "Anna",
        "buyerLastName": "Clark"
      },
      {
        "name": "Pioglitazone",
        "price": 306.56,
        "buyerFirstName": "Diana",
        "buyerLastName": "Harvey"
      },
      {
        "name": "Treatment Set TS336667",
        "price": 1466.47,
        "buyerFirstName": "Arthur",
        "buyerLastName": "Reynolds"
      }
    ]
  },
  {
    "firstName": "Rachel",
    "lastName": "Johnson",
    "soldProducts": [
      {
        "name": "ziprasidone hydrochloride",
        "price": 628.66,
        "buyerFirstName": "Anna",
        "buyerLastName": "Parker"
      }
    ]
  },
  {
    "firstName": "Patrick",
    "lastName": "King",
    "soldProducts": [
      {
        "name": "SNORING HP",
        "price": 53.59,
        "buyerLastName": "Fox"
      },
      {
        "name": "Isosorbide Mononitrate",
        "price": 789.91,
        "buyerFirstName": "Christine",
        "buyerLastName": "Gomez"
      },
      {
        "name": "XtraCare Foam Antibacterial Hand Wash",
        "price": 1251.97,
        "buyerFirstName": "Brandon",
        "buyerLastName": "Fuller"
      }
    ]
  },
  {
    "firstName": "Betty",
    "lastName": "Lawson",
    "soldProducts": [
      {
        "name": "Ringers",
        "price": 1054.37,
        "buyerFirstName": "Betty",
        "buyerLastName": "Ward"
      },
      {
        "name": "GOONG SECRET CALMING BATH",
        "price": 742.47,
        "buyerLastName": "Harrison"
      },
      {
        "name": "ROPINIROLE HYDROCHLORIDE",
        "price": 266.44,
        "buyerLastName": "Stewart"
      }
    ]
  },
  {
    "firstName": "Carl",
    "lastName": "Lawson",
    "soldProducts": [
      {
        "name": "PREMIER VALUE ALLERGY",
        "price": 1127.61,
        "buyerFirstName": "Carl",
        "buyerLastName": "Lawson"
      },
      {
        "name": "Enchanted Moments Mistletoe Kisses Hand Sanitizer",
        "price": 384.99,
        "buyerLastName": "Harrison"
      },
      {
        "name": "Pleo Lat",
        "price": 720.08,
        "buyerFirstName": "Betty",
        "buyerLastName": "Ward"
      }
    ]
  },
  {
    "firstName": "Nicole",
    "lastName": "Martinez",
    "soldProducts": [
      {
        "name": "No7 Protect and Perfect Foundation Sunscreen Broad Spectrum SPF 15 Cool Ivory",
        "price": 616.19,
        "buyerFirstName": "Betty",
        "buyerLastName": "Ward"
      }
    ]
  },
  {
    "firstName": "Chris",
    "lastName": "Mitchell",
    "soldProducts": [
      {
        "name": "ENALAPRIL MALEATE",
        "price": 210.42,
        "buyerFirstName": "Anna",
        "buyerLastName": "Parker"
      },
      {
        "name": "Metformin Hydrochloride",
        "price": 953.99,
        "buyerFirstName": "Patricia",
        "buyerLastName": "Cooper"
      },
      {
        "name": "CEDAX",
        "price": 342.86,
        "buyerFirstName": "Sarah",
        "buyerLastName": "Day"
      },
      {
        "name": "Ibuprofen",
        "price": 1088.04,
        "buyerFirstName": "Nicole",
        "buyerLastName": "Martinez"
      },
      {
        "name": "VITALUMIERE AQUA",
        "price": 1293.09,
        "buyerFirstName": "Gloria",
        "buyerLastName": "Alexander"
      },
      {
        "name": "NEO-POLY-BAC HYDRO",
        "price": 967.32,
        "buyerLastName": "Stewart"
      }
    ]
  },
  {
    "lastName": "Moreno",
    "soldProducts": [
      {
        "name": "Metoprolol Tartrate",
        "price": 1405.74,
        "buyerLastName": "Schmidt"
      },
      {
        "name": "Americaine",
        "price": 1165.75,
        "buyerFirstName": "Sarah",
        "buyerLastName": "Day"
      }
    ]
  },
  {
    "firstName": "Joshua",
    "lastName": "Murray",
    "soldProducts": [
      {
        "name": "equaline",
        "price": 520.45,
        "buyerFirstName": "Thomas",
        "buyerLastName": "Snyder"
      },
      {
        "name": "Protonix",
        "price": 466.70,
        "buyerFirstName": "Fred",
        "buyerLastName": "Barnes"
      }
    ]
  },
  {
    "firstName": "Anna",
    "lastName": "Parker",
    "soldProducts": [
      {
        "name": "Prednisone",
        "price": 1285.99,
        "buyerFirstName": "Diana",
        "buyerLastName": "Harvey"
      }
    ]
  },
  {
    "firstName": "Billy",
    "lastName": "Parker",
    "soldProducts": [
      {
        "name": "Peter Island Continous sunscreen kids",
        "price": 471.30,
        "buyerFirstName": "Bonnie",
        "buyerLastName": "Fox"
      }
    ]
  },
  {
    "firstName": "Emily",
    "lastName": "Parker",
    "soldProducts": [
      {
        "name": "Ibuprofen",
        "price": 1305.96,
        "buyerFirstName": "Amanda",
        "buyerLastName": "Frazier"
      },
      {
        "name": "Warfarin Sodium",
        "price": 770.05,
        "buyerFirstName": "Patricia",
        "buyerLastName": "Cooper"
      },
      {
        "name": "Pollens - Weeds and Garden Plants, Scotch Broom Cytisus scoparius",
        "price": 135.82,
        "buyerFirstName": "Diana",
        "buyerLastName": "Harvey"
      },
      {
        "name": "ANXIETY/STRESS RELIEF",
        "price": 324.66,
        "buyerFirstName": "Brenda",
        "buyerLastName": "Howell"
      }
    ]
  },
  {
    "firstName": "Christina",
    "lastName": "Patterson",
    "soldProducts": [
      {
        "name": "Fosphenytoin Sodium",
        "price": 1334.06,
        "buyerFirstName": "Anna",
        "buyerLastName": "Clark"
      }
    ]
  },
  {
    "firstName": "Jacqueline",
    "lastName": "Perez",
    "soldProducts": [
      {
        "name": "Prednisone",
        "price": 550.72,
        "buyerLastName": "Stewart"
      },
      {
        "name": "Ranitidine",
        "price": 926.64,
        "buyerFirstName": "Nicole",
        "buyerLastName": "Martinez"
      }
    ]
  },
  {
    "lastName": "Peterson",
    "soldProducts": [
      {
        "name": "Fair Foundation SPF 15",
        "price": 1394.24,
        "buyerLastName": "Thompson"
      }
    ]
  },
  {
    "firstName": "Arthur",
    "lastName": "Reynolds",
    "soldProducts": [
      {
        "name": "LANEIGE MYSTIC VEIL FOUNDATION",
        "price": 20.86,
        "buyerFirstName": "Christina",
        "buyerLastName": "Patterson"
      },
      {
        "name": "TYLENOL COLD MULTI-SYMPTOM DAYTIME",
        "price": 1010.81,
        "buyerLastName": "Baker"
      },
      {
        "name": "Spironolactone",
        "price": 933.69,
        "buyerFirstName": "Eugene",
        "buyerLastName": "Stewart"
      },
      {
        "name": "Acnezzol Base",
        "price": 710.60,
        "buyerFirstName": "Jennifer",
        "buyerLastName": "Riley"
      }
    ]
  },
  {
    "firstName": "Jennifer",
    "lastName": "Riley",
    "soldProducts": [
      {
        "name": "Amitiza",
        "price": 666.58,
        "buyerFirstName": "Arthur",
        "buyerLastName": "Reynolds"
      },
      {
        "name": "Labetalol Hydrochloride",
        "price": 1345.11,
        "buyerFirstName": "Betty",
        "buyerLastName": "Ward"
      }
    ]
  },
  {
    "firstName": "Sandra",
    "lastName": "Riley",
    "soldProducts": [
      {
        "name": "Alcohol Free Antiseptic",
        "price": 1486.07,
        "buyerFirstName": "Christina",
        "buyerLastName": "Patterson"
      }
    ]
  },
  {
    "lastName": "Schmidt",
    "soldProducts": [
      {
        "name": "Gehwol med Lipidro",
        "price": 421.24,
        "buyerFirstName": "Billy",
        "buyerLastName": "Parker"
      }
    ]
  },
  {
    "firstName": "Thomas",
    "lastName": "Snyder",
    "soldProducts": [
      {
        "name": "DAYWEAR PLUS MULTI PROTECTION TINTED MOISTURIZER",
        "price": 555.12,
        "buyerFirstName": "Emily",
        "buyerLastName": "Parker"
      },
      {
        "name": "Cefadroxil",
        "price": 1302.20,
        "buyerFirstName": "Paula",
        "buyerLastName": "Hill"
      }
    ]
  },
  {
    "firstName": "Ann",
    "lastName": "Stevens",
    "soldProducts": [
      {
        "name": "Topical 60 Sec Sodium Fluoride",
        "price": 1228.84,
        "buyerLastName": "Peterson"
      },
      {
        "name": "Homeopathic Rheumatism",
        "price": 967.08,
        "buyerFirstName": "Jennifer",
        "buyerLastName": "Riley"
      },
      {
        "name": "DIPYRIDAMOLE",
        "price": 1150.67,
        "buyerFirstName": "Christine",
        "buyerLastName": "Gomez"
      }
    ]
  },
  {
    "firstName": "Gary",
    "lastName": "Stevens",
    "soldProducts": [
      {
        "name": "Acetic Acid",
        "price": 1060.43,
        "buyerFirstName": "Patricia",
        "buyerLastName": "Fuller"
      },
      {
        "name": "MEDI-FIRST Non-Aspirin",
        "price": 1301.28,
        "buyerFirstName": "Arthur",
        "buyerLastName": "Reynolds"
      },
      {
        "name": "Butalbital, Aspirin and Caffeine",
        "price": 1010.98,
        "buyerFirstName": "Billy",
        "buyerLastName": "Parker"
      },
      {
        "name": "Foaming Hand Sanitizer",
        "price": 624.72,
        "buyerFirstName": "Thomas",
        "buyerLastName": "Snyder"
      }
    ]
  },
  {
    "lastName": "Stewart",
    "soldProducts": [
      {
        "name": "Allopurinol",
        "price": 336.81,
        "buyerFirstName": "Carl",
        "buyerLastName": "Lawson"
      },
      {
        "name": "Agaricus Equisetum Special Order",
        "price": 585.93,
        "buyerFirstName": "Wanda",
        "buyerLastName": "Harris"
      }
    ]
  },
  {
    "firstName": "Eugene",
    "lastName": "Stewart",
    "soldProducts": [
      {
        "name": "Smooth texture Orange flavor",
        "price": 976.65,
        "buyerFirstName": "Anna",
        "buyerLastName": "Clark"
      }
    ]
  },
  {
    "lastName": "Thompson",
    "soldProducts": [
      {
        "name": "Propranolol Hydrochloride",
        "price": 546.95,
        "buyerFirstName": "Betty",
        "buyerLastName": "Ward"
      },
      {
        "name": "Laser Block 100",
        "price": 1135.43,
        "buyerFirstName": "Fred",
        "buyerLastName": "Barnes"
      },
      {
        "name": "Cold and Cough",
        "price": 218.14,
        "buyerFirstName": "Wanda",
        "buyerLastName": "Harris"
      }
    ]
  },
  {
    "firstName": "Betty",
    "lastName": "Ward",
    "soldProducts": [
      {
        "name": "Care One Hemorrhoidal",
        "price": 932.18,
        "buyerFirstName": "Clarence",
        "buyerLastName": "Fowler"
      },
      {
        "name": "Budpak Hemorrhoid Anesthetic",
        "price": 1499.29,
        "buyerFirstName": "Diana",
        "buyerLastName": "Harvey"
      }
    ]
  },
  {
    "firstName": "Marie",
    "lastName": "Williamson",
    "soldProducts": [
      {
        "name": "U-max Multi BB",
        "price": 137.16,
        "buyerFirstName": "Chris",
        "buyerLastName": "Mitchell"
      },
      {
        "name": "Aquafresh",
        "price": 849.93,
        "buyerLastName": "Peterson"
      },
      {
        "name": "EMEND",
        "price": 1365.51,
        "buyerFirstName": "Diana",
        "buyerLastName": "Harvey"
      }
    ]
  }
]
